dop_library/__init__.py
dop_library/main.py
dop_library/run_results_table_schema.json
dop_library_dinigo-0.1.4.dist-info/WHEEL
dop_library_dinigo-0.1.4.dist-info/METADATA
dop_library_dinigo-0.1.4.dist-info/RECORD
