Metadata-Version: 2.1
Name: dop-library-dinigo
Version: 0.1.4
Summary: This package contains all the utils and functions that are used in the DOP framework.
Author: Daniel Iñigo
Author-email: daniel.inigo@datatonic.com
Requires-Python: >=3.7,<4.0
Classifier: Programming Language :: Python :: 3
Classifier: Programming Language :: Python :: 3.7
Classifier: Programming Language :: Python :: 3.8
Classifier: Programming Language :: Python :: 3.9
Classifier: Programming Language :: Python :: 3.10
Classifier: Programming Language :: Python :: 3.11
Requires-Dist: apache-airflow-providers-google (>=6,<7)
